up_ma_bfws/maBFWS
up_ma_bfws/__init__.py
up_ma_bfws/ma_bfws_planner.py
up_ma_bfws-0.0.4.dist-info/top_level.txt
up_ma_bfws-0.0.4.dist-info/WHEEL
up_ma_bfws-0.0.4.dist-info/RECORD
up_ma_bfws-0.0.4.dist-info/METADATA
