Metadata-Version: 2.1
Name: up-ma-bfws
Version: 0.0.4
Summary: up_ma_bfws
Author: UNIBS Team
Author-email: alberto.rovetta@unibs.it
License: APACHE
